{
    "configurations": [
        {
            "name": "config",
            "includePath": [
                "${workspaceFolder}/**",
                "${workspaceFolder}/NDSA",
                "c:/msys64/opt/devkitpro/libnds/include/",
                "c:/msys64/opt/devkitpro/libgba/include/",
                "/opt/devkitpro/libnds/include/",
                "/opt/devkitpro/libgba/include"
            ],
            "defines": [
                "_DEBUG",
                "UNICODE",
                "_UNICODE",
                "ARM9",
                "GBA"
            ],
            "compilerPath": "/opt/devkitpro/devkitARM/bin/arm-none-eabi-g++",
            "cStandard": "c17",
            "cppStandard": "c++11",
            "intelliSenseMode": "linux-gcc-arm"
        }
    ],
    "version": 4
}